app_version_updater/__init__.py
app_version_updater/client.py
app_version_updater/models.py
app_version_updater/server.py
app_version_updater/utils.py
app_version_updater-0.2.7.dist-info/METADATA
app_version_updater-0.2.7.dist-info/WHEEL
app_version_updater-0.2.7.dist-info/RECORD
