Metadata-Version: 2.3
Name: app-version-updater
Version: 0.2.7
Summary: 
Author: Andrey Linyushin
Author-email: 89202979894@mail.ru
Requires-Python: >=3.10
Classifier: Programming Language :: Python :: 3
Classifier: Programming Language :: Python :: 3.10
Classifier: Programming Language :: Python :: 3.11
Classifier: Programming Language :: Python :: 3.12
Classifier: Programming Language :: Python :: 3.13
Requires-Dist: aiohttp (>=3.11.18,<4.0.0)
Requires-Dist: requests (>=2.32.3,<3.0.0)
Requires-Dist: standarted-logger (>=0.0.6)
